{
  "generated_at": "2026-01-10T16:15:08.503198",
  "sample_size": 48,
  "date_range": "20251229 to 20260109",
  "overall_stats": {
    "total_bets": 48,
    "wins": 9,
    "win_rate": 0.1875,
    "places": 9,
    "place_rate": 0.1875,
    "avg_p_win": 0.2972916666666667
  },
  "winning_patterns": [
    {
      "pattern": "BELOW_THRESHOLD",
      "win_rate": "27.3%",
      "expected": "28.0%",
      "sample_size": 11,
      "action": "KEEP - this strategy is working"
    }
  ],
  "failing_patterns": [],
  "recommendations": [
    "CRITICAL: Win rate (18.8%) is significantly below predictions (29.7%). AI is overconfident. Consider increasing selectivity or adjusting probability estimates.",
    "EW bets: 42 bets, 21.4% place rate"
  ],
  "prompt_guidance": "\nHISTORICAL PERFORMANCE INSIGHTS (Last 48 bets):\n\nWHAT'S WORKING:\n- BELOW_THRESHOLD: 27.3% win rate (expected 28.0%)\n\nRECOMMENDATIONS:\n- CRITICAL: Win rate (18.8%) is significantly below predictions (29.7%). AI is overconfident. Consider increasing selectivity or adjusting probability estimates.\n- EW bets: 42 bets, 21.4% place rate\n"
}